<system>
	<name>KOI-2177</name>
	<rightascension>19 05 28</rightascension>
	<declination>+48 25 26</declination>
	<distance>917.94</distance>
	<star>
		<magJ errorminus="0.028" errorplus="0.028">14.167</magJ>
		<magH errorminus="0.04" errorplus="0.04">13.79</magH>
		<magK errorminus="0.04" errorplus="0.04">13.63</magK>
		<name>KOI-2177</name>
		<temperature errorminus="71.00" errorplus="71.00">5354.00</temperature>
		<radius errorminus="0.1500" errorplus="0.1500">0.7600</radius>
		<mass errorminus="0.0300" errorplus="0.0300">0.8590</mass>
		<age errorminus="3.8000" errorplus="3.8000">0.6000</age>
		<planet>
			<name>KOI-2177 b</name>
			<name>KOI-2177 01</name>
			<radius errorminus="0.05377" errorplus="0.05377">0.19958</radius>
			<period errorminus="1.4000000e-03" errorplus="1.4000000e-03">62.890800000000</period>
			<transittime errorminus="0.0077000" errorplus="0.0077000">2454972.1312000</transittime>
			<semimajoraxis>0.2940000</semimajoraxis>
			<temperature>378.0</temperature>
			<list>Kepler Objects of Interest</list>
			<description>This is a Kepler Object of Interest from the Q1-Q12 dataset. It has been flagged as a possible transit event but has not been confirmed to be a planet yet.</description>
			<istransiting>1</istransiting>
		</planet>
	</star>
</system>
