<system>
	<name>KOI-4043</name>
	<rightascension>19 41 16</rightascension>
	<declination>+40 12 32</declination>
	<star>
		<name>KOI-4043</name>
		<radius errorminus=".0000" errorplus="0.0000">1.0000</radius>
		<planet>
			<name>KOI-4043 b</name>
			<name>KOI-4043 01</name>
			<radius errorminus="0.04830" errorplus="0.04830">0.20413</radius>
			<period errorminus="5.30000e-06" errorplus="5.30000e-06">1.615901500000</period>
			<transittime errorminus="0.0006900" errorplus="0.0006900">2454964.5079200</transittime>
			<semimajoraxis errorminus="5.9e-08" errorplus="5.9e-08">0.0269551</semimajoraxis>
			<temperature errorminus=".0" errorplus="0.0">1553.1</temperature>
			<list>Kepler Objects of Interest</list>
		</planet>
	</star>
</system>
