<system>
	<id>KOI-1331</id>
	<name>KOI-1331</name>
	<rightascension>19 38 02</rightascension>
	<declination>+39 23 55</declination>
	<distance>497.827836482</distance>
	<star>
		<magV>15.238</magV>
		<temperature>4652</temperature>
		<radius>0.64</radius>
		<planet>
			<name>KOI 1331 b</name>
			<mass>0.00972953925877</mass>
			<radius>0.1576549</radius>
			<period>6.8009445</period>
			<semimajoraxis>0.063</semimajoraxis>
			<list>Kepler Objects of Interest</list>
			<description>This is a Kepler Object of Interest. It has been flagged as a possible transit event but might have not been confirmed to be a planet yet.</description>
		</planet>
		<name>KOI-1331</name>
	</star>
</system>
