<system>
	<name>KOI-1909</name>
	<rightascension>19 08 33</rightascension>
	<declination>+47 06 54</declination>
	<distance>450.39</distance>
	<star>
		<magJ errorminus="0.021" errorplus="0.021">11.710</magJ>
		<magH errorminus="0.023" errorplus="0.023">11.448</magH>
		<magK errorminus="0.013" errorplus="0.013">11.409</magK>
		<name>KOI-1909</name>
		<temperature errorminus="72.00" errorplus="72.00">6095.00</temperature>
		<radius errorminus="0.6600" errorplus="0.6600">1.0000</radius>
		<mass errorminus="0.1500" errorplus="0.1500">1.0600</mass>
		<age errorminus="1.7000" errorplus="1.7000">1.6000</age>
		<planet>
			<name>KOI-1909 b</name>
			<name>KOI-1909 01</name>
			<radius errorminus="0.08840" errorplus="0.08840">0.13487</radius>
			<period errorminus="9.6000000e-05" errorplus="9.6000000e-05">12.758079000000</period>
			<transittime errorminus="0.0028000" errorplus="0.0028000">2454966.9557000</transittime>
			<semimajoraxis>0.1090000</semimajoraxis>
			<temperature>815.0</temperature>
			<list>Kepler Objects of Interest</list>
			<description>This is a Kepler Object of Interest from the Q1-Q12 dataset. It has been flagged as a possible transit event but has not been confirmed to be a planet yet.</description>
			<istransiting>1</istransiting>
		</planet>
		<planet>
			<name>KOI-1909 c</name>
			<name>KOI-1909 02</name>
			<radius errorminus="0.06653" errorplus="0.06653">0.10115</radius>
			<period errorminus="4.6000000e-05" errorplus="4.6000000e-05">5.470371000000</period>
			<transittime errorminus="0.0030000" errorplus="0.0030000">2454964.4909000</transittime>
			<semimajoraxis>0.0620000</semimajoraxis>
			<temperature>1081.0</temperature>
			<list>Kepler Objects of Interest</list>
			<description>This is a Kepler Object of Interest from the Q1-Q12 dataset. It has been flagged as a possible transit event but has not been confirmed to be a planet yet.</description>
			<istransiting>1</istransiting>
		</planet>
		<planet>
			<name>KOI-1909 d</name>
			<name>KOI-1909 03</name>
			<radius errorminus="0.09113" errorplus="0.09113">0.14581</radius>
			<period errorminus="2.7000000e-04" errorplus="2.7000000e-04">25.098580000000</period>
			<transittime errorminus="0.0040000" errorplus="0.0040000">2454978.5671000</transittime>
			<semimajoraxis>0.1710000</semimajoraxis>
			<temperature>651.0</temperature>
			<list>Kepler Objects of Interest</list>
			<description>This is a Kepler Object of Interest from the Q1-Q12 dataset. It has been flagged as a possible transit event but has not been confirmed to be a planet yet.</description>
			<istransiting>1</istransiting>
		</planet>
	</star>
</system>
