<system>
	<id>KOI-2191</id>
	<name>KOI-2191</name>
	<rightascension>19 00 20</rightascension>
	<declination>+40 53 56</declination>
	<distance>242.26370164</distance>
	<star>
		<magV>14.911</magV>
		<tmperature>3845</tmperature>
		<radius>0.53</radius>
		<planet>
			<name>KOI 2191 b</name>
			<mass>0.00557313547965</mass>
			<radius>0.1202916</radius>
			<period>8.8478128</period>
			<semimajoraxis>0.069</semimajoraxis>
			<list>Kepler Objects of Interest</list>
			<description>This is a Kepler Object of Interest. It has been flagged as a possible transit event but might have not been confirmed to be a planet yet.</description>
		</planet>
		<name>KOI-2191</name>
	</star>
</system>
