<system>
	<name>KOI-4112</name>
	<rightascension>19 31 41</rightascension>
	<declination>+38 26 32</declination>
	<star>
		<name>KOI-4112</name>
		<radius errorminus=".0000" errorplus="0.0000">1.3490</radius>
		<planet>
			<name>KOI-4112 b</name>
			<name>KOI-4112 01</name>
			<radius errorminus="0.04557" errorplus="0.04557">0.12485</radius>
			<period errorminus="1.60000e-05" errorplus="1.60000e-05">2.435875000000</period>
			<transittime errorminus="0.0029000" errorplus="0.0029000">2454965.8915000</transittime>
			<semimajoraxis errorminus="1.6e-07" errorplus="1.6e-07">0.0377406</semimajoraxis>
			<temperature errorminus="15.0" errorplus="15.0">1715.0</temperature>
			<list>Kepler Objects of Interest</list>
		</planet>
	</star>
</system>
