<system>
	<name>KOI-0288</name>
	<rightascension>19 34 51</rightascension>
	<declination>+46 13 35</declination>
	<distance>390.33</distance>
	<star>
		<magB errorminus="0.08" errorplus="0.08">11.54</magB>
		<magV errorminus="0.08" errorplus="0.08">11.04</magV>
		<magJ errorminus="0.021" errorplus="0.021">10.011</magJ>
		<magH errorminus="0.021" errorplus="0.021">9.774</magH>
		<magK errorminus="0.014" errorplus="0.014">9.705</magK>
		<name>KOI-0288</name>
		<temperature errorminus="52.00" errorplus="52.00">6088.00</temperature>
		<radius errorminus="0.3000" errorplus="0.3000">1.9500</radius>
		<mass errorminus="0.1000" errorplus="0.1000">1.4100</mass>
		<age errorminus="0.5100" errorplus="0.5100">3.0500</age>
		<planet>
			<name>KOI-0288 b</name>
			<name>KOI-0288 01</name>
			<radius errorminus="0.04374" errorplus="0.04374">0.28433</radius>
			<period errorminus="5.8000000e-05" errorplus="5.8000000e-05">10.275394000000</period>
			<transittime errorminus="0.0019000" errorplus="0.0019000">2455010.2708000</transittime>
			<semimajoraxis>0.1040000</semimajoraxis>
			<temperature>1163.0</temperature>
			<list>Kepler Objects of Interest</list>
			<description>This is a Kepler Object of Interest from the Q1-Q12 dataset. It has been flagged as a possible transit event but has not been confirmed to be a planet yet.</description>
			<istransiting>1</istransiting>
		</planet>
	</star>
</system>
