<system>
	<name>KOI-2042</name>
	<rightascension>19 55 00</rightascension>
	<declination>+45 27 59</declination>
	<distance>1602.39</distance>
	<star>
		<magJ errorminus="0.023" errorplus="0.023">12.039</magJ>
		<magH errorminus="0.03" errorplus="0.03">11.84</magH>
		<magK errorminus="0.023" errorplus="0.023">11.764</magK>
		<name>KOI-2042</name>
		<temperature errorminus="145.00" errorplus="145.00">6634.00</temperature>
		<radius errorminus="1.4000" errorplus="1.4000">2.6000</radius>
		<mass errorminus="0.3600" errorplus="0.3600">1.6100</mass>
		<age errorminus="1.2000" errorplus="1.2000">1.8000</age>
		<planet>
			<name>KOI-2042 b</name>
			<name>KOI-2042 01</name>
			<radius errorminus="0.48299" errorplus="0.48299">0.86574</radius>
			<period errorminus="1.8000000e-03" errorplus="1.8000000e-03">63.072900000000</period>
			<transittime errorminus="0.0096000" errorplus="0.0096000">2455024.2539000</transittime>
			<semimajoraxis>0.3630000</semimajoraxis>
			<temperature>779.0</temperature>
			<list>Kepler Objects of Interest</list>
			<description>This is a Kepler Object of Interest from the Q1-Q12 dataset. It has been flagged as a possible transit event but has not been confirmed to be a planet yet.</description>
			<istransiting>1</istransiting>
		</planet>
	</star>
</system>
