<system>
	<name>KOI-3570</name>
	<rightascension>19 40 57</rightascension>
	<declination>+40 09 27</declination>
	<star>
		<name>KOI-3570</name>
		<radius errorminus=".0000" errorplus="0.0000">1.1360</radius>
		<planet>
			<name>KOI-3570 b</name>
			<name>KOI-3570 01</name>
			<radius errorminus="0.00000" errorplus="0.00000">2.69434</radius>
			<period errorminus=".00000e+00" errorplus="0.00000e+00">1.824629545210</period>
			<transittime errorminus="0.0000000" errorplus="0.0000000">2454965.8800450</transittime>
			<semimajoraxis errorminus=".0e+00" errorplus="0.0e+00">0.0303901</semimajoraxis>
			<temperature errorminus=".0" errorplus="0.0">1665.3</temperature>
			<list>Kepler Objects of Interest</list>
		</planet>
	</star>
</system>
