{
    "confirmedPlanets": 6256,
    "discoverymethods": {
        "RV": 1118,
        "imaging": 282,
        "microlensing": 283,
        "timing": 141,
        "transit": 4276
    },
    "discoveryyears": {
        "1992": 3,
        "1993": 0,
        "1994": 0,
        "1995": 3,
        "1996": 10,
        "1997": 1,
        "1998": 7,
        "1999": 16,
        "2000": 24,
        "2001": 16,
        "2002": 37,
        "2003": 32,
        "2004": 35,
        "2005": 42,
        "2006": 41,
        "2007": 67,
        "2008": 67,
        "2009": 111,
        "2010": 139,
        "2011": 216,
        "2012": 164,
        "2013": 188,
        "2014": 868,
        "2015": 173,
        "2016": 1552,
        "2017": 424,
        "2018": 372,
        "2019": 257,
        "2020": 250,
        "2021": 241,
        "2022": 477,
        "2023": 245,
        "2024": 178,
        "2025": 0
    },
    "files": 4780,
    "lastUpdate": 1719014400.0
}