{
    "confirmedPlanets": 5388,
    "discoverymethods": {
        "RV": 1036,
        "imaging": 217,
        "microlensing": 242,
        "timing": 74,
        "transit": 3767
    },
    "discoveryyears": {
        "1992": 3,
        "1993": 0,
        "1994": 0,
        "1995": 3,
        "1996": 7,
        "1997": 0,
        "1998": 6,
        "1999": 15,
        "2000": 24,
        "2001": 15,
        "2002": 31,
        "2003": 28,
        "2004": 35,
        "2005": 36,
        "2006": 39,
        "2007": 64,
        "2008": 67,
        "2009": 90,
        "2010": 136,
        "2011": 206,
        "2012": 146,
        "2013": 184,
        "2014": 870,
        "2015": 170,
        "2016": 1536,
        "2017": 218,
        "2018": 361,
        "2019": 237,
        "2020": 244,
        "2021": 216,
        "2022": 324,
        "2023": 77,
        "2024": 0
    },
    "files": 4088,
    "lastUpdate": 1686268800.0
}