{
    "confirmedPlanets": 7318,
    "discoverymethods": {
        "RV": 1137,
        "imaging": 927,
        "microlensing": 308,
        "timing": 207,
        "transit": 4458
    },
    "discoveryyears": {
        "1992": 9,
        "1993": 4,
        "1994": 2,
        "1995": 3,
        "1996": 12,
        "1997": 11,
        "1998": 22,
        "1999": 48,
        "2000": 61,
        "2001": 30,
        "2002": 85,
        "2003": 67,
        "2004": 70,
        "2005": 61,
        "2006": 115,
        "2007": 98,
        "2008": 110,
        "2009": 123,
        "2010": 173,
        "2011": 262,
        "2012": 204,
        "2013": 211,
        "2014": 913,
        "2015": 203,
        "2016": 1552,
        "2017": 576,
        "2018": 381,
        "2019": 265,
        "2020": 275,
        "2021": 246,
        "2022": 510,
        "2023": 264,
        "2024": 337,
        "2025": 15
    },
    "files": 5713,
    "lastUpdate": 1726099200.0
}