<planet>
	<id_exoplaneteu>HD 59686 b</id_exoplaneteu>
	<name>HD 59686 b</name>
	<id>HD 59686 b</id>
	<discoverymethod>RV</discoverymethod>
	<properties>
		<mass>5.25</mass>
		<radius />
		<orbit>
			<period>303</period>
			<semimajoraxis>0.911</semimajoraxis>
			<eccentricity />
			<inclination />
		</orbit>
	</properties>
	<star>
		<spectraltype />
		<mass />
		<radius />
		<metallicity />
		<temperature />
		<rightascension>07 31 48</rightascension>
		<declination>+17 05 09</declination>
		<angulardistance />
		<distance>92</distance>
		<magV>5.45</magV>
		<magI />
		<magH />
		<magJ />
		<magK />
	</star>
	<multiplicity>1</multiplicity>
	<discoveryyear>2003</discoveryyear>
	<lastupdate>11/01/03</lastupdate>
	<description />
	<new>0</new>
	<image />
	<imagedescription />
	<list>Confirmed planets</list>
</planet>
