<planet>
	<id_exoplaneteu>ups And c</id_exoplaneteu>
	<name>ups And c</name>
	<id>ups And c</id>
	<discoverymethod>RV</discoverymethod>
	<properties>
		<mass>14.57</mass>
		<radius />
		<orbit>
			<period>237.7</period>
			<semimajoraxis>0.861</semimajoraxis>
			<eccentricity>0.24</eccentricity>
			<inclination>8</inclination>
		</orbit>
	</properties>
	<star>
		<spectraltype>F8 V</spectraltype>
		<mass>1.27</mass>
		<radius>1.631</radius>
		<metallicity>0.09</metallicity>
		<rightascension>01 36 48</rightascension>
		<declination>+41 24 38</declination>
		<angulardistance>0.06392</angulardistance>
		<distance>13.47</distance>
		<magV>4.09</magV>
		<magI />
		<magH />
		<magJ />
		<magK />
	</star>
	<multiplicity>4</multiplicity>
	<discoveryyear>1999</discoveryyear>
	<lastupdate>11/05/11</lastupdate>
	<description />
	<new>0</new>
	<image />
	<imagedescription />
	<description />
	<new>0</new>
	<image />
	<imagedescription />
</planet>
