<system><distance>53.8</distance><declination>20 52 53</declination><star><metallicity errorplus="0.04" errorminus="0.04">0.31</metallicity><spectraltype>G5</spectraltype><name>HD 122562</name><planet><discoveryyear>2016</discoveryyear><period errorplus="104.0" errorminus="81.0">2777.0</period><eccentricity>0.71</eccentricity><periastron errorplus="1.3" errorminus="1.3">306.1</periastron><name>HD 122562 b</name><lastupdate>2016-02-10</lastupdate><periastrontime errorplus="2.0" errorminus="2.0">2455935.0</periastrontime><semimajoraxis errorplus="0.2" errorminus="0.2">4.1</semimajoraxis><mass><key name="@upperlimit">24.0</key></mass></planet><temperature errorplus="67.0" errorminus="67.0">4958.0</temperature><magV>7.69</magV><mass errorplus="0.13" errorminus="0.13">1.13</mass></star><name>HD 122562</name><rightascension>14 35 15</rightascension></system>
