<system><distance>37.44</distance><declination>10 02 29</declination><star><metallicity>-0.078</metallicity><radius>1.09</radius><spectraltype>G0</spectraltype><name>HD 106252</name><planet><discoveryyear>2002</discoveryyear><period errorplus="18.0" errorminus="18.0">1600.0</period><eccentricity>0.47</eccentricity><periastron errorplus="3.2" errorminus="3.2">292.2</periastron><name>HD 106252 b</name><lastupdate>2015-09-14</lastupdate><periastrontime errorplus="17.0" errorminus="17.0">51871.0</periastrontime><semimajoraxis>2.7</semimajoraxis><mass><key name="@upperlimit">32.9</key></mass><inclination errorplus="7.3" errorminus="160.2">166.7</inclination></planet><temperature>5754.0</temperature><age>5.02</age><magV>7.36</magV><mass>0.96</mass></star><name>HD 106252</name><rightascension>12 22 14</rightascension></system>
