<system>
	<name>HD 151450</name>
	<rightascension>16 48 02</rightascension>
	<declination>-15 57 52</declination>
	<distance errorminus="0.1295000" errorplus="0.1302000">43.6002000</distance>
	<star>
		<name>HD 151450</name>
		<radius errorminus="0.04" errorplus="0.05">1.17</radius>
		<magV errorminus="0.0300000" errorplus="0.0300000">7.4300000</magV>
		<magJ errorminus="0.0260000" errorplus="0.0260000">6.4250000</magJ>
		<magH errorminus="0.0340000" errorplus="0.0340000">6.1380000</magH>
		<magK errorminus="0.0240000" errorplus="0.0240000">6.0990000</magK>
		<mass errorminus="0.16" errorplus="0.16">1.14</mass>
		<temperature errorminus="85.79" errorplus="129.58">6091.98</temperature>
		<planet>
			<name>HD 151450 b</name>
			<semimajoraxis errorminus="0.007839" errorplus="0.007214">0.159926</semimajoraxis>
			<eccentricity errorminus="0.104250" errorplus="0.117074">0.495560</eccentricity>
			<periastron errorminus="21.6487" errorplus="28.2176">257.9968</periastron>
			<period errorminus="0.00539292" errorplus="0.00846431">21.89287913</period>
			<description>This planet was discovered by Feng et al. 2022. This was a ground based discovery. The parameters listed here have been imported into the Open Exoplanet Catalogue from the NASA Exoplanet Archive.</description>
			<mass errorminus="0.02170" errorplus="0.02215">0.11719</mass>
			<radius>0.607</radius>
			<discoverymethod>RV</discoverymethod>
			<discoveryyear>2022</discoveryyear>
			<list>Confirmed planets</list>
			<lastupdate>22/09/27</lastupdate>
		</planet>
		<planet>
			<name>HD 151450 c</name>
			<semimajoraxis errorminus="2.489583" errorplus="2.772321">14.100560</semimajoraxis>
			<eccentricity errorminus="0.080233" errorplus="0.108040">0.137994</eccentricity>
			<periastron errorminus="74.3708" errorplus="66.2988">31.1787</periastron>
			<inclination errorminus="8.858" errorplus="11.085">42.369</inclination>
			<period errorminus="4350.39093454" errorplus="5356.32955200">18144.76235720</period>
			<description>This planet was discovered by Feng et al. 2022. This was a ground based discovery. The parameters listed here have been imported into the Open Exoplanet Catalogue from the NASA Exoplanet Archive.</description>
			<mass errorminus="1.05117" errorplus="1.18600">5.14148</mass>
			<radius>1.150</radius>
			<discoverymethod>RV</discoverymethod>
			<discoveryyear>2022</discoveryyear>
			<list>Confirmed planets</list>
			<lastupdate>22/09/27</lastupdate>
		</planet>
	</star>
	<constellation>Ophiucus</constellation>
</system>
