<system><distance>89.8</distance><declination>-56 38 59</declination><star><metallicity errorplus="0.16" errorminus="0.16">0.1</metallicity><radius>1.21</radius><spectraltype>G2/G3 IV-V</spectraltype><name>HD 2039</name><planet><discoveryyear>2002</discoveryyear><period errorplus="23.0" errorminus="23.0">1120.0</period><eccentricity>0.67</eccentricity><periastron errorplus="3.6" errorminus="3.6">344.1</periastron><name>HD 2039 b</name><lastupdate>2016-01-19</lastupdate><periastrontime errorplus="13.0" errorminus="13.0">2452041.0</periastrontime><semimajoraxis errorplus="0.13" errorminus="0.13">2.23</semimajoraxis><mass><key name="@upperlimit">6.11</key></mass></planet><temperature errorplus="39.0" errorminus="39.0">5947.0</temperature><age>5.28</age><magV>9.01</magV><mass errorplus="0.05" errorminus="0.05">0.98</mass></star><name>HD 2039</name><rightascension>00 04 59</rightascension></system>
