<system>
	<name>HD 206255</name>
	<name>HIP 107160</name>
	<rightascension>21 42 21.8926</rightascension>
	<declination>-50 05 36.9978</declination>
	<distance>75.40</distance>
	<star>
		<name>HD 206255</name>
		<name>HIP 107160</name>
		<name>Gaia DR2 6561908626047094144</name>
		<name>TYC 8432-832-1</name>
		<magV errorminus="0.010" errorplus="0.010">7.618</magV>
		<magJ errorminus="0.029" errorplus="0.029">6.379</magJ>
		<magH errorminus="0.040" errorplus="0.040">6.070</magH>
		<magK errorminus="0.020" errorplus="0.020">5.979</magK>
		<mass errorminus="0.08" errorplus="0.08">1.42</mass>
		<temperature errorminus="99.00" errorplus="82.00">5635.00</temperature>
		<spectraltype>G5IV/V</spectraltype>
		<planet>
			<name>HD 206255 b</name>
			<name>HIP 107160 b</name>
			<name>Gaia DR2 6561908626047094144 b</name>
			<name>TYC 8432-832-1 b</name>
			<semimajoraxis errorminus="0.009000" errorplus="0.009000">0.461000</semimajoraxis>
			<eccentricity errorminus="0.110000" errorplus="0.110000">0.230000</eccentricity>
			<periastron errorminus="44.9000" errorplus="44.9000">86.9200</periastron>
			<period errorminus="0.31700000" errorplus="0.31700000">96.04500000</period>
			<description>This planet was discovered by Feng et al. 2019. This was a ground based discovery. The parameters listed here are those reported by Feng et al. 2019 and were imported into the Open Exoplanet Catalogue from the NASA Exoplanet Archive.</description>
			<mass errorminus="0.02234" errorplus="0.02234">0.10760</mass>
			<discoverymethod>RV</discoverymethod>
			<discoveryyear>2019</discoveryyear>
			<list>Confirmed planets</list>
			<lastupdate>19/05/23</lastupdate>
		</planet>
	</star>
	<constellation>Indus</constellation>
</system>
