<system><distance errorplus="2.7" errorminus="2.6">96.8</distance><declination>17 05 08</declination><star><metallicity errorplus="0.1" errorminus="0.1">0.15</metallicity><radius errorplus="0.3" errorminus="0.3">13.2</radius><spectraltype>K2 III</spectraltype><name>HD 59686 A</name><name>HR 2877, HIP 36616</name><planet><discoveryyear>2003</discoveryyear><period errorplus="0.26" errorminus="0.31">299.36</period><eccentricity>0.05</eccentricity><name>HD 59686 A b</name><lastupdate>2016-08-03</lastupdate><semimajoraxis errorplus="0.0006" errorminus="0.0007">1.086</semimajoraxis><mass><key name="@upperlimit">6.92</key></mass></planet><temperature errorplus="24.0" errorminus="24.0">4658.0</temperature><age>1.73</age><magV>5.45</magV><mass errorplus="0.2" errorminus="0.2">1.9</mass></star><name>HD 59686 A</name><rightascension>07 57 00</rightascension></system>
