<system>
	<name>Kepler-286</name>
	<name>KOI-1306</name>
	<name>KIC 10858691</name>
	<rightascension>19 22 42</rightascension>
	<declination>+48 17 39</declination>
	<distance>1188.84</distance>
	<star>
		<magJ errorminus="0.03" errorplus="0.03">14.39</magJ>
		<magH errorminus="0.05" errorplus="0.05">14.06</magH>
		<magK errorminus="0.07" errorplus="0.07">14.12</magK>
		<name>Kepler-286</name>
		<name>KOI-1306</name>
		<name>KIC 10858691</name>
		<temperature errorminus="31" errorplus="131">5580</temperature>
		<radius errorminus=".167" errorplus="0.167">0.863</radius>
		<mass errorminus="0.1000" errorplus="0.1000">1.0300</mass>
		<planet>
			<name>Kepler-286 b</name>
			<name>KOI-1306 b</name>
			<name>KOI-1306.01</name>
			<name>KIC 10858691 b</name>
			<name>KIC 10858691.01</name>
			<radius errorminus="0.02278" errorplus="0.02278">0.11300</radius>
			<period errorminus=".000009" errorplus="0.000009">1.796302</period>
			<transittime errorminus="0.0030700" errorplus="0.0030700">2454966.3305700</transittime>
			<list>Confirmed planets</list>
			<description>Kepler-286 b has been discovered by the Kepler spacecraft and was originally classified as a planet candidate. A new statistical analysis led by a team at NASA Ames Research Center has validated the planet with more than 99 percent confidence. Although many parameters of Kepler-286 b are still unknown, the object is highly unlikely to be a false positive.</description>
			<discoveryyear>2014</discoveryyear>
			<lastupdate>14/02/26</lastupdate>
			<discoverymethod>transit</discoverymethod>
			<istransiting>1</istransiting>
		</planet>
		<planet>
			<name>Kepler-286 c</name>
			<name>KOI-1306 c</name>
			<name>KOI-1306.02</name>
			<name>KIC 10858691 c</name>
			<name>KIC 10858691.02</name>
			<radius errorminus="0.02461" errorplus="0.02461">0.12485</radius>
			<period errorminus=".000023" errorplus="0.000023">3.468095</period>
			<transittime errorminus="0.0039200" errorplus="0.0039200">2454969.0031800</transittime>
			<list>Confirmed planets</list>
			<description>Kepler-286 c has been discovered by the Kepler spacecraft and was originally classified as a planet candidate. A new statistical analysis led by a team at NASA Ames Research Center has validated the planet with more than 99 percent confidence. Although many parameters of Kepler-286 c are still unknown, the object is highly unlikely to be a false positive.</description>
			<discoveryyear>2014</discoveryyear>
			<lastupdate>14/02/26</lastupdate>
			<discoverymethod>transit</discoverymethod>
			<istransiting>1</istransiting>
		</planet>
		<planet>
			<name>Kepler-286 d</name>
			<name>KOI-1306 d</name>
			<name>KOI-1306.03</name>
			<name>KIC 10858691 d</name>
			<name>KIC 10858691.03</name>
			<radius errorminus="0.02461" errorplus="0.02461">0.12120</radius>
			<period errorminus=".000054" errorplus="0.000054">5.914323</period>
			<transittime errorminus="0.0052400" errorplus="0.0052400">2454966.4869800</transittime>
			<list>Confirmed planets</list>
			<description>Kepler-286 d has been discovered by the Kepler spacecraft and was originally classified as a planet candidate. A new statistical analysis led by a team at NASA Ames Research Center has validated the planet with more than 99 percent confidence. Although many parameters of Kepler-286 d are still unknown, the object is highly unlikely to be a false positive.</description>
			<discoveryyear>2014</discoveryyear>
			<lastupdate>14/02/26</lastupdate>
			<discoverymethod>transit</discoverymethod>
			<istransiting>1</istransiting>
		</planet>
		<planet>
			<name>Kepler-286 e</name>
			<name>KOI-1306 e</name>
			<name>KOI-1306.04</name>
			<name>KIC 10858691 e</name>
			<name>KIC 10858691.04</name>
			<radius errorminus="0.03919" errorplus="0.03919">0.16130</radius>
			<period errorminus=".000370" errorplus="0.000370">29.221289</period>
			<transittime errorminus="0.0071800" errorplus="0.0071800">2454972.3301700</transittime>
			<list>Confirmed planets</list>
			<description>Kepler-286 e has been discovered by the Kepler spacecraft and was originally classified as a planet candidate. A new statistical analysis led by a team at NASA Ames Research Center has validated the planet with more than 99 percent confidence. Although many parameters of Kepler-286 e are still unknown, the object is highly unlikely to be a false positive.</description>
			<discoveryyear>2014</discoveryyear>
			<lastupdate>14/02/26</lastupdate>
			<discoverymethod>transit</discoverymethod>
			<istransiting>1</istransiting>
		</planet>
	</star>
</system>
