<system><distance>1051.0</distance><declination>46 36 08</declination><star><metallicity errorplus="0.15" errorminus="0.175">0.0</metallicity><radius errorplus="0.19" errorminus="0.11">1.03</radius><name>Kepler-1052</name><planet><discoveryyear>2016</discoveryyear><period errorplus="0.000126" errorminus="0.000126">34.8538276</period><radius errorplus="0.048" errorminus="0.028">0.261</radius><name>Kepler-1052 b</name><lastupdate>2016-05-12</lastupdate></planet><temperature errorplus="160.5" errorminus="173.26">5888.0</temperature><magK>13.305</magK><magJ>13.727</magJ><magH>13.393</magH><mass errorplus="0.08" errorminus="0.07">1.03</mass></star><name>Kepler-1052</name><rightascension>19 20 33</rightascension></system>
