<system><distance>867.0</distance><declination>44 08 36</declination><star><metallicity errorplus="0.146" errorminus="0.191">-0.09</metallicity><radius errorplus="0.11" errorminus="0.07">0.93</radius><name>Kepler-761</name><planet><discoveryyear>2016</discoveryyear><period errorplus="2.905e-05" errorminus="2.905e-05">10.12804789</period><radius errorplus="0.022" errorminus="0.015">0.181</radius><name>Kepler-761 b</name><lastupdate>2016-05-12</lastupdate></planet><temperature errorplus="130.9" errorminus="104.39">5706.0</temperature><magK>13.202</magK><magJ>13.563</magJ><magH>13.156</magH><mass errorplus="0.06" errorminus="0.06">0.95</mass></star><name>Kepler-761</name><rightascension>19 30 12</rightascension></system>
