<system><distance>1150.0</distance><declination>43 50 08</declination><star><metallicity errorplus="0.138" errorminus="0.155">0.03</metallicity><radius errorplus="0.2" errorminus="0.07">0.98</radius><name>Kepler-1286</name><planet><discoveryyear>2016</discoveryyear><period errorplus="6.812e-05" errorminus="6.812e-05">11.25402929</period><radius errorplus="0.04" errorminus="0.016">0.192</radius><name>Kepler-1286 b</name><lastupdate>2016-05-12</lastupdate></planet><temperature errorplus="74.56" errorminus="79.2">5753.0</temperature><magK>13.655</magK><magJ>14.017</magJ><magH>13.683</magH><mass errorplus="0.05" errorminus="0.05">1.0</mass></star><name>Kepler-1286</name><rightascension>18 15 30</rightascension></system>
