<system><declination>42 57 58</declination><star><metallicity errorplus="0.1" errorminus="0.1">0.15</metallicity><radius errorplus="0.14" errorminus="0.14">0.945</radius><name>Kepler-82</name><name>KOI-880, KIC 7366258, 2MASS J19312961+4257580 </name><planet><discoveryyear>2011</discoveryyear><period errorplus="9.9e-05" errorminus="9.9e-05">51.531855</period><radius errorplus="0.075" errorminus="0.075">0.503</radius><eccentricity>0.0</eccentricity><name>Kepler-82 c</name><lastupdate>2016-07-01</lastupdate><temperature>464.0</temperature><semimajoraxis>0.264</semimajoraxis><transittime errorplus="0.00099" errorminus="0.00099">2455007.11378</transittime><inclination>89.95</inclination></planet><planet><discoveryyear>2011</discoveryyear><period errorplus="6.5e-05" errorminus="6.5e-05">26.443794</period><radius errorplus="0.055" errorminus="0.055">0.367</radius><eccentricity>0.0</eccentricity><name>Kepler-82 b</name><lastupdate>2016-07-01</lastupdate><temperature>581.0</temperature><semimajoraxis>0.169</semimajoraxis><transittime errorplus="0.00138" errorminus="0.00138">2455027.12502</transittime><inclination>89.38</inclination></planet><planet><discoveryyear>2011</discoveryyear><period errorplus="1.2e-05" errorminus="1.2e-05">5.902206</period><radius errorplus="0.033" errorminus="0.033">0.22</radius><name>Kepler-82 e</name><lastupdate>2016-07-01</lastupdate><semimajoraxis>0.063</semimajoraxis><transittime errorplus="0.00115" errorminus="0.00115">2454969.78443</transittime></planet><planet><discoveryyear>2011</discoveryyear><period errorplus="5e-06" errorminus="5e-06">2.382961</period><radius errorplus="0.024" errorminus="0.024">0.158</radius><name>Kepler-82 d</name><lastupdate>2016-07-01</lastupdate><semimajoraxis>0.034</semimajoraxis><transittime errorplus="0.00132" errorminus="0.00132">2454968.08186</transittime></planet><temperature errorplus="100.0" errorminus="100.0">5428.0</temperature><magK>13.518</magK><magJ>13.879</magJ><magH>13.527</magH><mass errorplus="1.66" errorminus="1.66">0.85</mass></star><name>Kepler-82</name><rightascension>19 52 24</rightascension></system>
