<system><distance>1718.0</distance><declination>40 43 16</declination><star><metallicity errorplus="0.127" errorminus="0.147">0.04</metallicity><radius errorplus="0.6" errorminus="0.39">1.85</radius><name>Kepler-1626</name><planet><discoveryyear>2016</discoveryyear><period errorplus="2.851e-05" errorminus="2.851e-05">4.13962966</period><radius errorplus="0.059" errorminus="0.038">0.18</radius><name>Kepler-1626 b</name><lastupdate>2016-05-12</lastupdate></planet><temperature errorplus="286.4" errorminus="316.8">6826.0</temperature><magK>12.967</magK><magJ>13.255</magJ><magH>13.039</magH><mass errorplus="0.21" errorminus="0.2">1.51</mass></star><name>Kepler-1626</name><rightascension>19 30 01</rightascension></system>
