<system><declination>42 11 46</declination><star><metallicity>-0.039</metallicity><radius errorplus="0.5" errorminus="0.5">1.09</radius><name>Kepler-359</name><planet><discoveryyear>2014</discoveryyear><period errorplus="0.001453" errorminus="0.001453">77.095691</period><radius errorplus="0.17" errorminus="0.17">0.358</radius><name>Kepler-359 d</name><lastupdate>2014-03-06</lastupdate><semimajoraxis>0.372</semimajoraxis></planet><planet><discoveryyear>2014</discoveryyear><period errorplus="0.000545" errorminus="0.000545">57.68802</period><radius errorplus="0.178" errorminus="0.178">0.384</radius><name>Kepler-359 c</name><lastupdate>2014-03-06</lastupdate><semimajoraxis>0.307</semimajoraxis></planet><planet><discoveryyear>2014</discoveryyear><period errorplus="0.000202" errorminus="0.000202">25.563222</period><radius errorplus="0.146" errorminus="0.146">0.315</radius><name>Kepler-359 b</name><lastupdate>2014-03-06</lastupdate><semimajoraxis>0.178</semimajoraxis></planet><temperature errorplus="250.0" errorminus="250.0">6248.0</temperature><magK>14.487</magK><magJ>14.736</magJ><magH>14.43</magH><mass>1.07</mass></star><name>Kepler-359</name><rightascension>19 17 37</rightascension></system>
