<system>
	<name>PH-2</name>
	<name>KIC 12735740</name>
	<rightascension>19 19 03</rightascension>
	<declination>+51 57 45.36</declination>
	<distance>369.8</distance>
	<star>
		<name>PH-2</name>
		<name>Kepler-86</name>
		<name>KOI-3663</name>
		<name>KIC 12735740</name>
		<name>2MASS 19190326+5157453</name>
		<metallicity>-0.07</metallicity>
		<temperature>6529</temperature>
		<mass>0.94</mass>
		<radius>1.0</radius>
		<planet>
			<name>PH-2 b</name>
			<name>KOI-3663.01</name>
			<name>KOI-3663 b</name>
			<name>KIC 12735740 b</name>
			<name>2MASS 19190326+5157453 b</name>
			<name>Planet Hunters 2 b</name>
			<name>Kepler-86 b</name>
			<list>Confirmed planets</list>
			<period>282.5255</period>
			<eccentricity>0.41</eccentricity>
			<periastron>3.43774677</periastron>
			<inclination>89.83</inclination>
			<semimajoraxis>0.828</semimajoraxis>
			<radius>0.922238</radius>
			<temperature>281</temperature>
			<transittime unit="MJD">2455195.570</transittime>
			<description>The exoplanet PH-2 b was discovered by citizen scientists using an online tool at planethunters.org. The planet is a gas giant and could be located in the star's habitable zone. The system might also have a faint binary companion.</description>
			<image>PH2</image>
			<imagedescription>Artistic rendition of a sunset view from the perspective of an imagined Earth-like moon orbiting the giant planet, PH2 b. 
			
Image Credit: H. Giguere, M. Giguere/Yale University</imagedescription>
			<discoverymethod>transit</discoverymethod>
			<lastupdate>14/03/25</lastupdate>
			<discoveryyear>2013</discoveryyear>
			<istransiting>1</istransiting>
		</planet>
	</star>
	<videolink>http://youtu.be/qHvb9mewXJo</videolink>
</system>
