<system>
	<name>Psi-1 Draconis</name>
	<name>ψ1 Dra</name>
	<name>ψ1 Draconis</name>
	<name>psi01 Dra</name>
	<name>psi01 Draconis</name>
	<rightascension>17 41 56.35536</rightascension>
	<declination>+72 08 55.8481</declination>
	<distance errorminus="0.06" errorplus="0.06">22.93</distance>
	<binary>
		<name>Psi-1 Draconis</name>
		<name>ψ1 Dra</name>
		<name>ψ1 Draconis</name>
		<name>psi01 Dra</name>
		<name>psi01 Draconis</name>
		<name>31 Dra</name>
		<name>31 Draconis</name>
		<name>Gliese 694.1</name>
		<name>GJ 694.1</name>
		<name>GJ 9602</name>
		<name>WDS J17419+7209</name>
		<separation unit="arcsec">30.104</separation>
		<separation unit="AU">690</separation>
		<positionangle>15.49</positionangle>
		<binary>
			<name>HD 162003</name>
			<name>HIP 86614</name>
			<name>TYC 4436-1425-1</name>
			<name>SAO 8890</name>
			<name>BD+72 804</name>
			<name>STF 2241 A</name>
			<period errorminus="160" errorplus="160">6649</period>
			<eccentricity errorminus="0.004" errorplus="0.004">0.674</eccentricity>
			<periastron errorminus="0.7" errorplus="0.7">32.9</periastron>
			<semimajoraxis errorminus="0.1" errorplus="0.1">8.7</semimajoraxis>
			<periastrontime errorminus="162" errorplus="162">2450515</periastrontime>
			<star>
				<name>Psi-1 Draconis A</name>
				<name>ψ1 Dra A</name>
				<name>ψ1 Draconis A</name>
				<name>psi01 Dra A</name>
				<name>psi01 Draconis A</name>
				<name>31 Dra A</name>
				<name>31 Draconis A</name>
				<name>HD 162003 A</name>
				<name>HIP 86614 A</name>
				<name>TYC 4436-1425-1 A</name>
				<name>SAO 8890 A</name>
				<name>HR 6636 A</name>
				<name>Gliese 694.1 A</name>
				<name>GJ 694.1 A</name>
				<name>GJ 9602 A</name>
				<name>BD+72 804 A</name>
				<name>2MASS J17415635+7208561</name>
				<name>WDS J17419+7209 A</name>
				<mass>1.430</mass>
				<magB>5.00</magB>
				<magV>4.56</magV>
				<magR>4.3</magR>
				<magI>4.1</magI>
				<magJ errorminus="0.264" errorplus="0.264">3.803</magJ>
				<magH errorminus="0.248" errorplus="0.248">3.648</magH>
				<magK errorminus="0.362" errorplus="0.362">3.502</magK>
				<spectraltype>F5IV-V</spectraltype>
				<temperature errorminus="56" errorplus="56">6546</temperature>
				<metallicity errorminus="0.07" errorplus="0.07">-0.10</metallicity>
				<age errorminus="0.3" errorplus="0.3">2.3</age>
			</star>
			<star>
				<name>Psi-1 Draconis C</name>
				<name>ψ1 Dra C</name>
				<name>ψ1 Draconis C</name>
				<name>psi01 Dra C</name>
				<name>psi01 Draconis C</name>
				<name>31 Dra C</name>
				<name>31 Draconis C</name>
				<name>HD 162003 B</name>
				<name>HIP 86614 B</name>
				<name>TYC 4436-1425-1 B</name>
				<name>SAO 8890 A</name>
				<name>HR 6636 B</name>
				<name>Gliese 694.1 C</name>
				<name>GJ 694.1 C</name>
				<name>GJ 9602 C</name>
				<name>BD+72 804 B</name>
				<spectraltype>K/M</spectraltype>
				<mass errorminus="0.005" errorplus="0.005" type="msini">0.526</mass>
			</star>
		</binary>
		<star>
			<name>Psi-1 Draconis B</name>
			<name>ψ1 Dra B</name>
			<name>ψ1 Draconis B</name>
			<name>psi01 Dra B</name>
			<name>psi01 Draconis B</name>
			<name>31 Dra B</name>
			<name>31 Draconis B</name>
			<name>HD 162004</name>
			<name>HIP 86620</name>
			<name>TYC 4436-1424-1</name>
			<name>SAO 8891</name>
			<name>HR 6637</name>
			<name>Gliese 694.1 B</name>
			<name>GJ 694.1 B</name>
			<name>GJ 9602 B</name>
			<name>BD+72 805</name>
			<name>2MASS J17415811+7209251</name>
			<name>WDS J17419+7209 B</name>
			<name>STF 2241 B</name>
			<magB>6.261</magB>
			<magV>5.699</magV>
			<magR>5.2</magR>
			<magI>5.0</magI>
			<magJ>5.00</magJ>
			<magH>4.59</magH>
			<magK>4.53</magK>
			<spectraltype>G0V</spectraltype>
			<mass errorminus="0.07" errorplus="0.07">1.19</mass>
			<temperature errorminus="20" errorplus="20">6213</temperature>
			<metallicity errorminus="0.04" errorplus="0.04">0.00</metallicity>
			<age errorminus="0.3" errorplus="0.3">2.5</age>
			<planet>
				<name>Psi-1 Draconis B b</name>
				<name>ψ1 Dra B b</name>
				<name>ψ1 Draconis B b</name>
				<name>psi01 Dra B b</name>
				<name>psi01 Draconis B b</name>
				<period errorminus="42" errorplus="42">3117</period>
				<mass errorminus="0.10" errorplus="0.10" type="msini">1.53</mass>
				<eccentricity errorminus="0.05" errorplus="0.05">0.40</eccentricity>
				<periastron errorminus="9" errorplus="9">64</periastron>
				<semimajoraxis errorminus="0.04" errorplus="0.04">4.43</semimajoraxis>
				<periastrontime errorminus="76" errorplus="76">2449344</periastrontime>
				<discoverymethod>RV</discoverymethod>
				<discoveryyear>2015</discoveryyear>
				<description>Psi-1 Draconis is a triple star system containing the spectroscopic binary Psi-1 Draconis AC, and their distant companion Psi-1 Draconis B. The radial velocities of Psi-1 Draconis B indicate the presence of a jovian planet on an eccentric, long-period orbit and a trend indicating the presence of an additional companion. The trend is not compatible with being caused by Psi-1 Draconis AC, so indicates the presence of an additional, likely substellar object outside the orbit of the known jovian planet.</description>
				<lastupdate>15/12/28</lastupdate>
				<list>Confirmed planets</list>
				<list>Planets in binary systems, S-type</list>
			</planet>
		</star>
	</binary>
</system>
